scraipe_cyber/__init__.py
scraipe_cyber/ukraine/__init__.py
scraipe_cyber/ukraine/cert_ua_scraper.py
scraipe_cyber/ukraine/ukraine_cyber_multi_scraper.py
scraipe_cyber-0.1.3.dist-info/LICENSE
scraipe_cyber-0.1.3.dist-info/METADATA
scraipe_cyber-0.1.3.dist-info/WHEEL
scraipe_cyber-0.1.3.dist-info/RECORD
