Metadata-Version: 2.3
Name: scraipe-cyber
Version: 0.1.3
Summary: Scraipe scrapers for cyber research.
License: MIT
Author: Nibs
Requires-Python: >=3.10,<4.0
Classifier: License :: OSI Approved :: MIT License
Classifier: Programming Language :: Python :: 3
Classifier: Programming Language :: Python :: 3.10
Classifier: Programming Language :: Python :: 3.11
Classifier: Programming Language :: Python :: 3.12
Classifier: Programming Language :: Python :: 3.13
Requires-Dist: scraipe[extended] (>=0.1.30,<0.2.0)
Project-URL: Homepage, https://github.com/snpm/scraipe-cyber-research
